nanocodec_torch/__init__.py
nanocodec_torch/layers/__init__.py
nanocodec_torch/layers/activations.py
nanocodec_torch/layers/conv.py
nanocodec_torch/models/__init__.py
nanocodec_torch/models/audio_codec.py
nanocodec_torch/models/decoder.py
nanocodec_torch/models/encoder.py
nanocodec_torch/models/quantizer_fixed.py
nanocodec_torch/utils/__init__.py
nanocodec_torch/utils/safetensors_loader.py
nanocodec_torch/utils/weight_loader_v2.py
nanocodec_torch-1.0.0.dist-info/licenses/LICENSE
nanocodec_torch-1.0.0.dist-info/licenses/NOTICE
nanocodec_torch-1.0.0.dist-info/METADATA
nanocodec_torch-1.0.0.dist-info/WHEEL
nanocodec_torch-1.0.0.dist-info/top_level.txt
nanocodec_torch-1.0.0.dist-info/RECORD
