Metadata-Version: 2.4
Name: nanocodec-torch
Version: 1.0.0
Summary: PyTorch implementation of NVIDIA NeMo NanoCodec - Ultra-lightweight neural audio codec (0.6 kbps, 1764:1 compression)
Author-email: NineNineSix <ulan@nineninesix.ai>
License:                                  Apache License
Project-URL: Homepage, https://github.com/nineninesix-ai/nanocodec-torch
Project-URL: Repository, https://github.com/nineninesix-ai/nanocodec-torch
Project-URL: Issues, https://github.com/nineninesix-ai/nanocodec-torch/issues
Keywords: pytorch,audio-codec,neural-codec,audio-compression,speech-compression,nanocodec,finite-scalar-quantization,hifigan,ultra-low-bitrate,machine-learning,deep-learning
Classifier: Development Status :: 5 - Production/Stable
Classifier: Intended Audience :: Developers
Classifier: Intended Audience :: Science/Research
Classifier: License :: OSI Approved :: Apache Software License
Classifier: Operating System :: OS Independent
Classifier: Programming Language :: Python :: 3
Classifier: Programming Language :: Python :: 3.10
Classifier: Programming Language :: Python :: 3.11
Classifier: Programming Language :: Python :: 3.12
Classifier: Topic :: Multimedia :: Sound/Audio
Classifier: Topic :: Multimedia :: Sound/Audio :: Conversion
Classifier: Topic :: Scientific/Engineering :: Artificial Intelligence
Requires-Python: >=3.10
License-File: LICENSE
License-File: NOTICE
Requires-Dist: torch>=2.0.0
Requires-Dist: numpy>=1.24.0
Requires-Dist: huggingface-hub>=0.35.0
Requires-Dist: safetensors>=0.4.0
Provides-Extra: dev
Requires-Dist: pytest>=7.0; extra == "dev"
Requires-Dist: pytest-cov>=4.0; extra == "dev"
Requires-Dist: black>=23.0; extra == "dev"
Requires-Dist: flake8>=6.0; extra == "dev"
Requires-Dist: mypy>=1.0; extra == "dev"
Provides-Extra: audio
Requires-Dist: torchaudio>=2.0.0; extra == "audio"
Requires-Dist: soundfile>=0.12.0; extra == "audio"
Dynamic: license-file
